LICENSE
MANIFEST.in
README.md
setup.cfg
setup.py
versioneer.py
object_store_abstraction/MultiTenantObjectStore.py
object_store_abstraction/RepositoryBaseClass.py
object_store_abstraction/RepositoryCachingBaseClass.py
object_store_abstraction/RepositoryObjBaseClass.py
object_store_abstraction/__init__.py
object_store_abstraction/_version.py
object_store_abstraction/makeDictJSONSerializable.py
object_store_abstraction/objectStores.py
object_store_abstraction/objectStores_DynamoDB.py
object_store_abstraction/objectStores_Memory.py
object_store_abstraction/objectStores_Migrating.py
object_store_abstraction/objectStores_SQLAlchemy.py
object_store_abstraction/objectStores_SimpleFileStore.py
object_store_abstraction/objectStores_TenantAware.py
object_store_abstraction/objectStores_base.py
object_store_abstraction/paginatedResult.py
object_store_abstraction/paginatedResultIterator.py
object_store_abstraction.egg-info/PKG-INFO
object_store_abstraction.egg-info/SOURCES.txt
object_store_abstraction.egg-info/dependency_links.txt
object_store_abstraction.egg-info/not-zip-safe
object_store_abstraction.egg-info/requires.txt
object_store_abstraction.egg-info/top_level.txt
object_store_abstraction/DoubleStringIndex/DoubleStringIndexClass.py
object_store_abstraction/DoubleStringIndex/ObjectStoresConnectionContextExtensionBase.py
object_store_abstraction/DoubleStringIndex/ObjectStoresConnectionContextExtension_Caching.py
object_store_abstraction/DoubleStringIndex/ObjectStoresConnectionContextExtension_DynamoDB.py
object_store_abstraction/DoubleStringIndex/ObjectStoresConnectionContextExtension_Memory.py
object_store_abstraction/DoubleStringIndex/ObjectStoresConnectionContextExtension_Migrating.py
object_store_abstraction/DoubleStringIndex/ObjectStoresConnectionContextExtension_SQLAlchemy.py
object_store_abstraction/DoubleStringIndex/ObjectStoresConnectionContextExtension_SimpleFileStore.py
object_store_abstraction/DoubleStringIndex/ObjectStoresConnectionContextExtension_TenantAware.py
object_store_abstraction/DoubleStringIndex/__init__.py
object_store_abstraction/objectStoresPackage/__init__.py
object_store_abstraction/objectStoresPackage/caching/CachePolicy.py
object_store_abstraction/objectStoresPackage/caching/ConnectionContext.py
