Metadata-Version: 2.4
Name: object_store_abstraction
Version: 0.4.12
Summary: Python package which provides an abstract object store
Home-page: https://github.com/rmetcalf9/object_store_abstraction
Author: Robert Metcalf
Author-email: rmetcalf9@googlemail.com
License: MIT
License-File: LICENSE
Requires-Dist: pytz==2025.2
Requires-Dist: sortedcontainers==2.4.0
Requires-Dist: pyjwt==2.8.0
Requires-Dist: sqlalchemy==1.3.1
Requires-Dist: PyMySQL==0.9.3
Requires-Dist: python-dateutil==2.8.1
Requires-Dist: boto3==1.26.97
Dynamic: author
Dynamic: author-email
Dynamic: home-page
Dynamic: license
Dynamic: license-file
Dynamic: requires-dist
Dynamic: summary
